setup.py
mango_pulsar_client/Bookies.py
mango_pulsar_client/BrokerStats.py
mango_pulsar_client/Brokers.py
mango_pulsar_client/Clusters.py
mango_pulsar_client/MangoPulsar.py
mango_pulsar_client/MangoPulsarAdmin.py
mango_pulsar_client/Namespaces.py
mango_pulsar_client/NonPersistentTopic.py
mango_pulsar_client/PersistentTopic.py
mango_pulsar_client/ResourceQuotas.py
mango_pulsar_client/Schemas.py
mango_pulsar_client/Tenants.py
mango_pulsar_client/__init__.py
mango_pulsar_client.egg-info/PKG-INFO
mango_pulsar_client.egg-info/SOURCES.txt
mango_pulsar_client.egg-info/dependency_links.txt
mango_pulsar_client.egg-info/requires.txt
mango_pulsar_client.egg-info/top_level.txt